fuzzaprox/__init__.py
fuzzaprox/fuzzaprox.py
fuzzaprox/services/__init__.py
fuzzaprox/services/data_approx_classes.py
fuzzaprox/services/data_service.py
fuzzaprox/transformations/__init__.py
fuzzaprox/transformations/fuzzy_set.py
fuzzaprox/transformations/fuzzy_set_basic.py
fuzzaprox/transformations/operations.py
fuzzaprox/transformations/transform.py
fuzzaprox-0.0.2.dist-info/licenses/LICENCE
test/__init__.py
test/test_fuzzaprox.py
fuzzaprox-0.0.2.dist-info/METADATA
fuzzaprox-0.0.2.dist-info/WHEEL
fuzzaprox-0.0.2.dist-info/top_level.txt
fuzzaprox-0.0.2.dist-info/RECORD
