Metadata-Version: 2.4
Name: fuzzaprox
Version: 0.0.2
Summary: F-transform approximation over residuated lattices
Author-email: Radovan Zahornadsky <rad.zahornadsky@gmail.com>
License: MIT
Requires-Python: >=3.10
License-File: LICENCE
Requires-Dist: numpy
Dynamic: license-file
